blurhashify/__init__.py
blurhashify/cli.py
blurhashify/constants.py
blurhashify-0.1.1.dist-info/METADATA
blurhashify-0.1.1.dist-info/WHEEL
blurhashify-0.1.1.dist-info/entry_points.txt
blurhashify-0.1.1.dist-info/licenses/LICENSE
blurhashify-0.1.1.dist-info/RECORD
