Metadata-Version: 2.1
Name: blurhashify
Version: 0.1.1
Summary: Generate BlurHash images from an existing image.
Project-URL: Source, https://gitlab.com/joaommpalmeiro/blurhashify
Author-email: João Palmeiro <jm.palmeiro@campus.fct.unl.pt>
License-Expression: MIT
License-File: LICENSE
Requires-Python: >=3.7
Requires-Dist: blurhash-python==1.1.3
Requires-Dist: click==8.1.3
Requires-Dist: joblib==1.2.0
